datawalk/__init__.py
datawalk/errors.py
datawalk/filters/__init__.py
datawalk/filters/all.py
datawalk/filters/first.py
datawalk/py.typed
datawalk/selectors/by_key.py
datawalk/selectors/by_slice.py
datawalk-0.2.0.dist-info/WHEEL
datawalk-0.2.0.dist-info/METADATA
datawalk-0.2.0.dist-info/RECORD
