Metadata-Version: 2.3
Name: datawalk
Version: 0.2.0
Summary: Fetch values from nested data structures
Requires-Python: >=3.10
